dbpedia_sparql_simplify/__init__.py
dbpedia_sparql_simplify/sparql_query.py
dbpedia_sparql_simplify/sparql_util.py
dbpedia_sparql_simplify-1.0.4.dist-info/LICENSE.txt
dbpedia_sparql_simplify-1.0.4.dist-info/METADATA
dbpedia_sparql_simplify-1.0.4.dist-info/RECORD
dbpedia_sparql_simplify-1.0.4.dist-info/WHEEL
dbpedia_sparql_simplify-1.0.4.dist-info/entry_points.txt
dbpedia_sparql_simplify-1.0.4.dist-info/top_level.txt
